core/__init__.py
core/config.py
core/core.py
core/error_handler.py
core/exceptions.py
core/interfaces.py
core/logging.py
core/metrics_collector.py
core/py.typed
core/types.py
semantic_scholar_mcp/__init__.py
semantic_scholar_mcp/__main__.py
semantic_scholar_mcp/agent.py
semantic_scholar_mcp/api_client.py
semantic_scholar_mcp/instruction_loader.py
semantic_scholar_mcp/models.py
semantic_scholar_mcp/pdf_processor.py
semantic_scholar_mcp/project.py
semantic_scholar_mcp/py.typed
semantic_scholar_mcp/server.py
semantic_scholar_mcp/utils.py
semantic_scholar_mcp/dashboard/__init__.py
semantic_scholar_mcp/dashboard/server.py
semantic_scholar_mcp/dashboard/stats.py
semantic_scholar_mcp/dashboard/static/css/style.css
semantic_scholar_mcp/dashboard/static/js/app.js
semantic_scholar_mcp/dashboard/templates/index.html
semantic_scholar_mcp/resources/tool_instructions/author/batch_get_authors.md
semantic_scholar_mcp/resources/tool_instructions/author/batch_get_authors.yml
semantic_scholar_mcp/resources/tool_instructions/author/get_author.md
semantic_scholar_mcp/resources/tool_instructions/author/get_author.yml
semantic_scholar_mcp/resources/tool_instructions/author/get_author_papers.md
semantic_scholar_mcp/resources/tool_instructions/author/get_author_papers.yml
semantic_scholar_mcp/resources/tool_instructions/author/search_authors.md
semantic_scholar_mcp/resources/tool_instructions/author/search_authors.yml
semantic_scholar_mcp/resources/tool_instructions/dataset/get_dataset_download_links.md
semantic_scholar_mcp/resources/tool_instructions/dataset/get_dataset_download_links.yml
semantic_scholar_mcp/resources/tool_instructions/dataset/get_dataset_info.md
semantic_scholar_mcp/resources/tool_instructions/dataset/get_dataset_info.yml
semantic_scholar_mcp/resources/tool_instructions/dataset/get_dataset_releases.md
semantic_scholar_mcp/resources/tool_instructions/dataset/get_dataset_releases.yml
semantic_scholar_mcp-0.4.0.dist-info/METADATA
semantic_scholar_mcp-0.4.0.dist-info/WHEEL
semantic_scholar_mcp-0.4.0.dist-info/entry_points.txt
semantic_scholar_mcp-0.4.0.dist-info/licenses/LICENSE
semantic_scholar_mcp-0.4.0.dist-info/RECORD
