Metadata-Version: 2.4
Name: semantic-scholar-mcp
Version: 0.4.0
Summary: MCP server for Semantic Scholar API integration with Claude Desktop
Project-URL: Homepage, https://github.com/hy20191108/semantic-scholar-mcp
Project-URL: Bug Tracker, https://github.com/hy20191108/semantic-scholar-mcp/issues
Project-URL: Repository, https://github.com/hy20191108/semantic-scholar-mcp
Project-URL: Documentation, https://github.com/hy20191108/semantic-scholar-mcp#readme
Author-email: hy20191108 <zwwp9976@gmail.com>
License: MIT
License-File: LICENSE
Keywords: api,claude,mcp,papers,research,semantic-scholar
Classifier: Development Status :: 4 - Beta
Classifier: Intended Audience :: Developers
Classifier: License :: OSI Approved :: MIT License
Classifier: Programming Language :: Python :: 3
Classifier: Programming Language :: Python :: 3.10
Classifier: Programming Language :: Python :: 3.11
Classifier: Programming Language :: Python :: 3.12
Classifier: Programming Language :: Python :: 3.13
Requires-Python: >=3.10
Requires-Dist: flask>=3.1.2
Requires-Dist: httpx>=0.27.0
Requires-Dist: mcp[cli]>=1.12.3
Requires-Dist: pydantic>=2.0.0
Requires-Dist: pymupdf4llm>=0.0.27
Requires-Dist: python-dotenv>=1.0.0
Requires-Dist: pyyaml>=6.0.2
Requires-Dist: tenacity>=8.2.0
